[{"path":"/romaxa55/MegaV_Public","title":"Overview","count":330,"uniques":291},{"path":"/Romaxa55/MegaV_Public","title":"Overview","count":323,"uniques":269},{"path":"/Romaxa55/MegaV_Public/releases/tag/v4.1.7","title":"/releases/tag/v4.1.7","count":106,"uniques":91},{"path":"/Romaxa55/MegaV_Public/tree/main/subs","title":"/tree/main/subs","count":91,"uniques":66},{"path":"/Romaxa55/MegaV_Public/blob/main/subs/all.txt","title":"/blob/main/subs/all.txt","count":79,"uniques":61},{"path":"/Romaxa55/MegaV_Public/blob/main/subs/vless.txt","title":"/blob/main/subs/vless.txt","count":72,"uniques":51},{"path":"/Romaxa55/MegaV_Public/blob/main/README_RU.md","title":"/blob/main/README_RU.md","count":50,"uniques":30},{"path":"/Romaxa55/MegaV_Public/releases","title":"/releases","count":38,"uniques":35},{"path":"/Romaxa55/MegaV_Public/blob/main/README_ZH.md","title":"/blob/main/README_ZH.md","count":31,"uniques":19},{"path":"/Romaxa55/MegaV_Public/blob/main/README_FA.md","title":"/blob/main/README_FA.md","count":19,"uniques":15}]